{"dataflow":{"dfKey":"e8fd78f1-007d-441a-8aa5-1370f818d071","name":"DT","tags":null,"description":null,"definition":"{\"name\":\"DT\",\"engineVariableName\":\"\",\"components\":[],\"isDeleteWorkSchemaTable\":\"N\"}","parameters":"[{\"name\":\"limit_rows\",\"defValueInInteractiveMode\":\"limit 10\",\"defValueInBatchMode\":\"limit 1000\"}]","version":3,"maxComponentId":0,"livyOptions":null,"isDeleted":"N","userName":null,"type":"componenttestcase","environmentName":"","folderPath":"DB Flow/TESTCASE","workSchemaName":"PostgreSQL_Workschemaqa111"},"analysis":[],"datamodels":[],"tagDetails":[{"tagName":"","additinalInfo":"{\"colourCode\":\"#f3c142ff\"}"}],"dataCompares":[]}