{"dataflow":{"dfKey":"bec67bec-bb1d-4440-bcb4-c8ed0d89a6f2","name":"Dataflow_67708","tags":null,"description":null,"definition":"{\"name\":\"Dataflow_67708\",\"engineVariableName\":\"\",\"components\":[{\"udfNames\":[],\"componentId\":0,\"componentName\":\"startComponent\",\"tableName\":\"\",\"category\":\"Start\",\"componentType\":\"UDF\",\"rank\":0,\"dataSourceName\":\"\",\"displayRows\":0,\"dependencies\":[],\"className\":\"com.datagaps.dataflow.models.UDFComponent\",\"executionOption\":\"\",\"excludeNotification\":\"Y\"},{\"visuals\":[{\"id\":\"c0802f9b17ea656ddd95\",\"name\":\"Card\",\"datasetName\":\"Card_486867\",\"visualType\":\"card\"},{\"id\":\"f21422c0280d5687e7ad\",\"name\":\"Card\",\"datasetName\":\"Card_647924\",\"visualType\":\"card\"},{\"id\":\"607e2054dcea83c042a1\",\"name\":\"Slicer\",\"datasetName\":\"Slicer_357757\",\"visualType\":\"slicer\"},{\"id\":\"730800c4a8850b9074d3\",\"name\":\"Slicer\",\"datasetName\":\"Slicer_397537\",\"visualType\":\"slicer\"},{\"id\":\"871cce970a59337e6aca\",\"name\":\"Slicer\",\"datasetName\":\"Slicer_894298\",\"visualType\":\"slicer\"},{\"id\":\"94398a657704ca4573d5\",\"name\":\"Reseller Sales\",\"datasetName\":\"Reseller_Sales_213659\",\"visualType\":\"card\"},{\"id\":\"12af70316c3253966000\",\"name\":\"Reseller Sales\",\"datasetName\":\"Reseller_Sales_149194\",\"visualType\":\"card\"},{\"id\":\"6576eb00a504ebb1dc03\",\"name\":\"Reseller Sales\",\"datasetName\":\"Reseller_Sales_342145\",\"visualType\":\"card\"},{\"id\":\"26e825524d8765101c1e\",\"name\":\"VacationHours by DepartmentName\",\"datasetName\":\"VacationHours_by_DepartmentName_925265\",\"visualType\":\"treemap\"},{\"id\":\"58357dda2c064b2a7926\",\"name\":\"SickLeaveHours by FirstName\",\"datasetName\":\"SickLeaveHours_by_FirstName_186623\",\"visualType\":\"treemap\"},{\"id\":\"e82a296c7cd22b4305d2\",\"name\":\"NumberEmployees by DepartmentName\",\"datasetName\":\"NumberEmployees_by_DepartmentName_247012\",\"visualType\":\"pieChart\"},{\"id\":\"73b3b66ba34955e22344\",\"name\":\"AnnualRevenue by MinPaymentType\",\"datasetName\":\"AnnualRevenue_by_MinPaymentType_442079\",\"visualType\":\"pieChart\"},{\"id\":\"d3c2391a2ed7cd2ba866\",\"name\":\"AnnualRevenue by DepartmentName\",\"datasetName\":\"AnnualRevenue_by_DepartmentName_933114\",\"visualType\":\"donutChart\"},{\"id\":\"7303bb8f0b209a3e22b8\",\"name\":\"AnnualSales by DepartmentName\",\"datasetName\":\"AnnualSales_by_DepartmentName_392921\",\"visualType\":\"pieChart\"}],\"slicers\":\"\",\"bookmark\":\"\",\"pageName\":\"ReportSection8137b9a17acea7b9a7d1\",\"reportId\":\"83f9eb3b-b794-4a99-835b-3505a5678c7b\",\"embedUrl\":\"https://app.powerbi.com/reportEmbed?reportId\\u003d83f9eb3b-b794-4a99-835b-3505a5678c7b\\u0026groupId\\u003d0bef08a5-4499-4697-8d8c-1dcc99ddce77\\u0026w\\u003d2\\u0026config\\u003deyJjbHVzdGVyVXJsIjoiaHR0cHM6Ly9XQUJJLUlORElBLUNFTlRSQUwtQS1QUklNQVJZLXJlZGlyZWN0LmFuYWx5c2lzLndpbmRvd3MubmV0IiwiZW1iZWRGZWF0dXJlcyI6eyJtb2Rlcm5FbWJlZCI6dHJ1ZSwidXNhZ2VNZXRyaWNzVk5leHQiOnRydWV9fQ%3d%3d\",\"reportName\":\"Demo/Adventure Works/Duplicate of Employee analysis\",\"reportType\":\"PowerBIReport\",\"datasets\":[\"b2134f31-88db-4571-aba5-210277bb5542\"],\"userIdentity\":\"\",\"workSpaceName\":\"\",\"componentId\":2,\"componentName\":\"Power BI 2\",\"tableName\":\"\",\"category\":\"Source\",\"componentType\":\"Power BI\",\"rank\":0,\"dataSourceName\":\"PowerBiMaster_Srikanth\",\"displayRows\":0,\"dependencies\":[],\"className\":\"com.datagaps.dataflow.models.PowerBiComponent\",\"isCheckpointEnabled\":\"N\",\"dataSourceLogicalName\":\"\",\"executionOption\":\"\",\"excludeNotification\":\"N\"},{\"visuals\":[{\"id\":\"6d992ffad58218dba46d\",\"name\":\"Annual Revenue\",\"datasetName\":\"Annual_Revenue_536802\",\"visualType\":\"card\"},{\"id\":\"328a10b0c060282d07c8\",\"name\":\"Annual Sales\",\"datasetName\":\"Annual_Sales_586251\",\"visualType\":\"card\"},{\"id\":\"77e8e4d0dca10e0bcae2\",\"name\":\"Min Payment Amt\",\"datasetName\":\"Min_Payment_Amt_371651\",\"visualType\":\"card\"},{\"id\":\"1c872fa4a85058704c58\",\"name\":\"Male Customers\",\"datasetName\":\"Male_Customers_922370\",\"visualType\":\"card\"},{\"id\":\"aca37b9f8565ab6b0226\",\"name\":\"Female Customers\",\"datasetName\":\"Female_Customers_769176\",\"visualType\":\"card\"},{\"id\":\"4d75cfe532c0d350c8c7\",\"name\":\"Total Children\",\"datasetName\":\"Total_Children_846695\",\"visualType\":\"card\"},{\"id\":\"ed6612a2c60e4a70de10\",\"name\":\"Yearly Income\",\"datasetName\":\"Yearly_Income_422431\",\"visualType\":\"card\"},{\"id\":\"3bc426c5a58a0b0de825\",\"name\":\"Sales by Gender\",\"datasetName\":\"Sales_by_Gender_477268\",\"visualType\":\"pieChart\"},{\"id\":\"32b8668ca0d9770754b4\",\"name\":\"Total Sales for Children\",\"datasetName\":\"Total_Sales_for_Children_377095\",\"visualType\":\"pieChart\"},{\"id\":\"99002c358c7bead2850c\",\"name\":\"YearlyIncome by Gender\",\"datasetName\":\"YearlyIncome_by_Gender_671277\",\"visualType\":\"clusteredColumnChart\"},{\"id\":\"f80ccf617ce36de94055\",\"name\":\"SalesAmount by SalesTerritoryCountry\",\"datasetName\":\"SalesAmount_by_SalesTerritoryCountry_880189\",\"visualType\":\"map\"},{\"id\":\"c50149af00b033ba0c34\",\"name\":\"Slicer\",\"datasetName\":\"Slicer_525696\",\"visualType\":\"slicer\"},{\"id\":\"3f581aaa6a0d89737c94\",\"name\":\"Quarter\",\"datasetName\":\"Quarter_878271\",\"visualType\":\"slicer\"},{\"id\":\"876cb45753b76c753ae4\",\"name\":\"Table\",\"datasetName\":\"Table_873580\",\"visualType\":\"tableEx\"},{\"id\":\"561847a6bfa8ec159483\",\"name\":\"Slicer\",\"datasetName\":\"Slicer_655248\",\"visualType\":\"slicer\"}],\"slicers\":\"\",\"bookmark\":\"\",\"pageName\":\"ReportSection\",\"reportId\":\"83f9eb3b-b794-4a99-835b-3505a5678c7b\",\"embedUrl\":\"https://app.powerbi.com/reportEmbed?reportId\\u003d83f9eb3b-b794-4a99-835b-3505a5678c7b\\u0026groupId\\u003d0bef08a5-4499-4697-8d8c-1dcc99ddce77\\u0026w\\u003d2\\u0026config\\u003deyJjbHVzdGVyVXJsIjoiaHR0cHM6Ly9XQUJJLUlORElBLUNFTlRSQUwtQS1QUklNQVJZLXJlZGlyZWN0LmFuYWx5c2lzLndpbmRvd3MubmV0IiwiZW1iZWRGZWF0dXJlcyI6eyJtb2Rlcm5FbWJlZCI6dHJ1ZSwidXNhZ2VNZXRyaWNzVk5leHQiOnRydWV9fQ%3d%3d\",\"reportName\":\"Demo/Adventure Works/Customer Analysis\",\"reportType\":\"PowerBIReport\",\"datasets\":[\"b2134f31-88db-4571-aba5-210277bb5542\"],\"userIdentity\":\"\",\"workSpaceName\":\"\",\"componentId\":3,\"componentName\":\"Power BI 3\",\"tableName\":\"\",\"category\":\"Source\",\"componentType\":\"Power BI\",\"rank\":0,\"dataSourceName\":\"PowerBiMaster_Srikanth\",\"displayRows\":0,\"dependencies\":[2],\"className\":\"com.datagaps.dataflow.models.PowerBiComponent\",\"isCheckpointEnabled\":\"N\",\"dataSourceLogicalName\":\"\",\"executionOption\":\"allparentpassorfail\",\"excludeNotification\":\"N\"}],\"isDeleteWorkSchemaTable\":\"N\"}","parameters":"[{\"name\":\"limit_rows\",\"defValueInInteractiveMode\":\"limit 10\",\"defValueInBatchMode\":\"limit 1000\"}]","version":3,"maxComponentId":3,"livyOptions":null,"isDeleted":"N","userName":null,"type":"dataflow","environmentName":"","folderPath":"Dataflow","workSchemaName":null},"analysis":[],"datamodels":[],"tagDetails":[],"dataCompares":[]}