{"pipelineKey":"89de9b76-e49f-421a-bdf2-f0d4c7437198","name":"Pipeline_7029","description":"","definition":"{\"workerLimit\":4,\"tasks\":[{\"children\":[\"6878bd10-7670-471f-9732-c78ffda59a91\",\"d198d0b6-3574-4abe-91c8-f37ff2bb65b5\",\"2cd3570c-50f9-47dd-8062-a4dda96e72cb\"],\"iteratee\":{},\"id\":\"Terminator\",\"type\":\"Terminator\"},{\"parent\":[\"Terminator\"],\"stopOnTaskFailure\":\"N\",\"dfName\":\"Dataflow_8261\",\"stopDependentTasks\":\"N\",\"label\":\"Data\",\"type\":\"runDataFlow\",\"dfKey\":\"6a155006-0d60-4c85-8ae6-cb7b97483d66\",\"livyServer\":\"146_livy\",\"children\":[],\"iteratee\":{},\"name\":\"df_Dataflow_8261_735130\",\"id\":\"6878bd10-7670-471f-9732-c78ffda59a91\",\"parameters\":\"{\\\"limit_rows\\\":\\\"limit 1000\\\"}\"},{\"parent\":[\"Terminator\"],\"stopOnTaskFailure\":\"N\",\"dfName\":\"Dataflow_6751\",\"stopDependentTasks\":\"N\",\"label\":\"Data\",\"type\":\"runDataFlow\",\"dfKey\":\"3623fccf-f1d1-40b3-ac58-2141b9bef2e4\",\"livyServer\":\"146_livy\",\"children\":[],\"iteratee\":{},\"name\":\"df_Dataflow_6751_370127\",\"id\":\"d198d0b6-3574-4abe-91c8-f37ff2bb65b5\",\"parameters\":\"{\\\"limit_rows\\\":\\\"limit 1000\\\"}\"},{\"parent\":[\"Terminator\"],\"stopOnTaskFailure\":\"N\",\"dfName\":\"Dataflow_8014\",\"stopDependentTasks\":\"N\",\"label\":\"Data\",\"type\":\"runDataFlow\",\"dfKey\":\"633487bc-d634-4cd6-8793-a9c92f887107\",\"livyServer\":\"146_livy\",\"children\":[],\"iteratee\":{},\"name\":\"df_Dataflow_8014_604527\",\"id\":\"2cd3570c-50f9-47dd-8062-a4dda96e72cb\",\"parameters\":\"{\\\"limit_rows\\\":\\\"limit 1000\\\"}\"}]}"}