{"dataflow":{"dfKey":"3f56c8b3-d43c-470e-87ae-31291729874f","name":"DB Flow4449","tags":null,"description":null,"definition":"{\"name\":\"DB Flow4449\",\"engineVariableName\":\"\",\"components\":[],\"isDeleteWorkSchemaTable\":\"N\"}","parameters":"[{\"name\":\"limit_rows\",\"defValueInInteractiveMode\":\"limit 10\",\"defValueInBatchMode\":\"limit 1000\"}]","version":3,"maxComponentId":0,"livyOptions":null,"isDeleted":"N","userName":null,"type":"componenttestcase","environmentName":"","folderPath":"DB Flow","workSchemaName":null},"analysis":[],"datamodels":[],"tagDetails":[],"dataCompares":[]}