{"dataflow":{"dfKey":"343f3e0c-64ff-45d7-8bb1-ed291fe712fd","name":"DB Flow2708_Copy","tags":null,"description":null,"definition":"{\"name\":\"DB Flow2708_Copy\",\"engineVariableName\":\"\",\"components\":[{\"format\":\"csv\",\"enableSchema\":\"N\",\"schema\":[],\"fileMetadata\":[],\"enableTrim\":\"N\",\"columns\":[{\"columnName\":\"EMPNO\",\"tableColumnName\":\"EMPNO\",\"mappedDataType\":\"numeric\",\"supportedDataType\":[\"integer\",\"float\",\"numeric\",\"character varying\"],\"dataTypelength\":\"\"},{\"columnName\":\"ENAME\",\"tableColumnName\":\"ENAME\",\"mappedDataType\":\"character varying\",\"supportedDataType\":[\"character varying\",\"text\"],\"dataTypelength\":\"2000\"},{\"columnName\":\"JOB\",\"tableColumnName\":\"JOB\",\"mappedDataType\":\"character varying\",\"supportedDataType\":[\"character varying\",\"text\"],\"dataTypelength\":\"2000\"},{\"columnName\":\"MGR\",\"tableColumnName\":\"MGR\",\"mappedDataType\":\"numeric\",\"supportedDataType\":[\"integer\",\"float\",\"numeric\",\"character varying\"],\"dataTypelength\":\"\"},{\"columnName\":\"HIREDATE\",\"tableColumnName\":\"HIREDATE\",\"mappedDataType\":\"character varying\",\"supportedDataType\":[\"character varying\",\"text\"],\"dataTypelength\":\"2000\"},{\"columnName\":\"SAL\",\"tableColumnName\":\"SAL\",\"mappedDataType\":\"numeric\",\"supportedDataType\":[\"integer\",\"float\",\"numeric\",\"character varying\"],\"dataTypelength\":\"\"},{\"columnName\":\"COMM\",\"tableColumnName\":\"COMM\",\"mappedDataType\":\"numeric\",\"supportedDataType\":[\"integer\",\"float\",\"numeric\",\"character varying\"],\"dataTypelength\":\"\"},{\"columnName\":\"DEPTNO\",\"tableColumnName\":\"DEPTNO\",\"mappedDataType\":\"numeric\",\"supportedDataType\":[\"integer\",\"float\",\"numeric\",\"character varying\"],\"dataTypelength\":\"\"}],\"componentId\":1,\"componentName\":\"File 1\",\"tableName\":\"File_1_6477_Nwhh\",\"category\":\"Source\",\"componentType\":\"TestCase File\",\"rank\":0,\"dataSourceName\":\"CSV_shared_71\",\"displayRows\":50,\"dependencies\":[],\"options\":{\"delimiter\":\",\",\"multiLine\":\"true\",\"header\":\"true\",\"inferSchema\":\"true\",\"path\":\"emp1.csv\"},\"className\":\"com.datagaps.dataflow.models.FileComponent\",\"isCheckpointEnabled\":\"N\",\"executionOption\":\"allparentpassorfail\",\"excludeNotification\":\"N\"},{\"format\":\"New folder\",\"enableSchema\":\"N\",\"schema\":[],\"fileMetadata\":[],\"enableTrim\":\"N\",\"columns\":[{\"columnName\":\"EMPNO\",\"tableColumnName\":\"EMPNO\",\"mappedDataType\":\"numeric\",\"supportedDataType\":[\"integer\",\"float\",\"numeric\",\"character varying\"],\"dataTypelength\":\"\"},{\"columnName\":\"ENAME\",\"tableColumnName\":\"ENAME\",\"mappedDataType\":\"character varying\",\"supportedDataType\":[\"character varying\",\"text\"],\"dataTypelength\":\"2000\"},{\"columnName\":\"JOB\",\"tableColumnName\":\"JOB\",\"mappedDataType\":\"character varying\",\"supportedDataType\":[\"character varying\",\"text\"],\"dataTypelength\":\"2000\"},{\"columnName\":\"MGR\",\"tableColumnName\":\"MGR\",\"mappedDataType\":\"numeric\",\"supportedDataType\":[\"integer\",\"float\",\"numeric\",\"character varying\"],\"dataTypelength\":\"\"},{\"columnName\":\"HIREDATE\",\"tableColumnName\":\"HIREDATE\",\"mappedDataType\":\"character varying\",\"supportedDataType\":[\"character varying\",\"text\"],\"dataTypelength\":\"2000\"},{\"columnName\":\"SAL\",\"tableColumnName\":\"SAL\",\"mappedDataType\":\"numeric\",\"supportedDataType\":[\"integer\",\"float\",\"numeric\",\"character varying\"],\"dataTypelength\":\"\"},{\"columnName\":\"COMM\",\"tableColumnName\":\"COMM\",\"mappedDataType\":\"numeric\",\"supportedDataType\":[\"integer\",\"float\",\"numeric\",\"character varying\"],\"dataTypelength\":\"\"},{\"columnName\":\"DEPTNO\",\"tableColumnName\":\"DEPTNO\",\"mappedDataType\":\"numeric\",\"supportedDataType\":[\"integer\",\"float\",\"numeric\",\"character varying\"],\"dataTypelength\":\"\"}],\"componentId\":2,\"componentName\":\"File 2\",\"tableName\":\"File_2_813\",\"category\":\"Source\",\"componentType\":\"TestCase File\",\"rank\":0,\"dataSourceName\":\"CSV_shared_71\",\"displayRows\":50,\"dependencies\":[],\"options\":{\"delimiter\":\",\",\"multiLine\":\"true\",\"header\":\"true\",\"inferSchema\":\"true\",\"path\":\"New folder\"},\"className\":\"com.datagaps.dataflow.models.FileComponent\",\"isCheckpointEnabled\":\"N\",\"executionOption\":\"allparentpassorfail\",\"excludeNotification\":\"N\"},{\"jdbcProfileOption\":{\"count\":\"Y\",\"countDistinct\":\"Y\",\"avg\":\"Y\",\"sum\":\"Y\",\"min\":\"Y\",\"max\":\"Y\",\"minLength\":\"Y\",\"maxLength\":\"Y\",\"isNull\":\"Y\"},\"query\":\"select actor_id,first_name,last_name,last_update from sakila.actor\",\"profileColumns\":[{\"columnName\":\"actor_id\",\"dataType\":\"INT\",\"profile\":\"Y\"},{\"columnName\":\"first_name\",\"dataType\":\"VARCHAR\",\"profile\":\"Y\"},{\"columnName\":\"last_name\",\"dataType\":\"VARCHAR\",\"profile\":\"Y\"},{\"columnName\":\"last_update\",\"dataType\":\"DATE\",\"profile\":\"Y\"}],\"easyQueryDefJson\":{\"sqlQuery\":\"\"},\"componentId\":3,\"componentName\":\"JDBC PROFILE 3\",\"tableName\":\"JDBC_PROFILE_3_2247\",\"category\":\"Data Reconciliation\",\"componentType\":\"JDBC PROFILE\",\"rank\":0,\"dataSourceName\":\"MySQL8\",\"displayRows\":0,\"dependencies\":[],\"className\":\"com.datagaps.dataflow.models.JDBCProfileComponent\",\"executionOption\":\"allparentpassorfail\",\"excludeNotification\":\"N\"},{\"sourceDataFrame\":\"JDBC_PROFILE_3_2247\",\"targetDataFrame\":\"JDBC_PROFILE_3_2247\",\"mapping\":[{\"sourceColumn\":\"actor_id\",\"sourceType\":\"INT\",\"targetColumn\":\"actor_id\",\"targetType\":\"INT\"},{\"sourceColumn\":\"first_name\",\"sourceType\":\"VARCHAR\",\"targetColumn\":\"first_name\",\"targetType\":\"VARCHAR\"},{\"sourceColumn\":\"last_name\",\"sourceType\":\"VARCHAR\",\"targetColumn\":\"last_name\",\"targetType\":\"VARCHAR\"},{\"sourceColumn\":\"last_update\",\"sourceType\":\"DATE\",\"targetColumn\":\"last_update\",\"targetType\":\"DATE\"}],\"allowedVariance\":0.0,\"componentId\":4,\"componentName\":\"JDBC Profile Compare 4\",\"tableName\":\"JDBC_Profile_Compare_4_8569\",\"category\":\"Source\",\"componentType\":\"JDBC Profile Compare\",\"rank\":0,\"displayRows\":0,\"dependencies\":[3],\"className\":\"com.datagaps.dataflow.models.JDBCProfileCompareComponent\",\"executionOption\":\"allparentpassorfail\",\"excludeNotification\":\"N\"},{\"query\":\"select * from File_2_813\",\"isTable\":\"Y\",\"componentId\":5,\"componentName\":\"SQL 5\",\"tableName\":\"SQL_5_8892\",\"category\":\"Processor\",\"componentType\":\"TestCase SQL\",\"rank\":0,\"dataSourceName\":\"\",\"displayRows\":50,\"dependencies\":[1,2],\"className\":\"com.datagaps.dataflow.models.SQLComponent\",\"executionOption\":\"allparentpassorfail\",\"excludeNotification\":\"N\"}],\"isDeleteWorkSchemaTable\":\"N\"}","parameters":"[{\"name\":\"limit_rows\",\"defValueInInteractiveMode\":\"limit 10\",\"defValueInBatchMode\":\"limit 1000\"}]","version":3,"maxComponentId":5,"livyOptions":null,"isDeleted":"N","userName":null,"type":"componenttestcase","environmentName":"","folderPath":"DB Flow","workSchemaName":"PostgreSQL_Workschemaqa"},"analysis":[],"datamodels":[],"tagDetails":[],"dataCompares":[]}