{"name":"Datamodel_7363","description":null,"dataSourceName":null,"tableDataModels":[{"tableName":"CHANNELS","schemaName":"TESTDATA","description":null,"columns":[{"columnName":"CHANNEL_ID","description":null,"dataType":"NUMBER","isNull":"Y","attributeName":null,"entityName":null,"columnOrder":1,"columnLength":"22","columnAlias":null,"additionalInfo":null}],"rules":[{"ruleName":"SQL Query Rule_3489","definition":"{\"severity\":\"Medium\",\"ruleQuery\":\"select * from TESTDATA.CHANNELS where rownum <=111\",\"active\":\"Yes\",\"threshold\":\"0\",\"schemaName\":\"TESTDATA\",\"dataQuery\":\"select count(*) from TESTDATA.CHANNELS\",\"dataQualityDimension\":\"Validity\",\"ruleTypeLabel\":\"SQL Query\",\"unit\":\"Percentage\",\"primaryColumn\":\"CHANNEL_ID\",\"recordsCount\":\"0\",\"columnNames\":\"\",\"successCriteria\":\"No bad records found\",\"ruleConditionType\":\"bad records\",\"ruleType\":\"SQLQuery\",\"percentage\":\"0\",\"name\":\"SQL query\",\"id\":\"\",\"operation\":\"<\",\"workSchemaId\":\"0\"}","description":null,"ruleType":"SQLQuery","ruleOrder":0,"tableName":"CHANNELS","columnName":"CHANNEL_ID","isActive":"Y","dataQualityDimension":"Validity","severity":"Medium","customFieldsValues":[],"ruleCategory":null,"isValid":null,"ruleKey":"a6dd1f79-4d57-4ccd-9ff8-ebb0e4afae1e"}],"relations":null,"sdvTemplate":null,"sampleDataSettingsJson":null,"datasourceName":null,"datasourceType":null,"uniqueColumns":null}],"workschemaName":null,"dmkey":"23558104-363c-47b9-b934-f460ce826bf3"}