{"name":"Datamodel_439","description":null,"dataSourceName":null,"tableDataModels":[{"tableName":"t_feature_audit_20220117","schemaName":"public","description":null,"columns":[{"columnName":"activity_dt","description":null,"dataType":"timestamp without time zone","isNull":"Y","attributeName":null,"entityName":null,"columnOrder":10,"columnLength":null,"columnAlias":null,"additionalInfo":null},{"columnName":"partition_date","description":null,"dataType":"date","isNull":"Y","attributeName":null,"entityName":null,"columnOrder":9,"columnLength":null,"columnAlias":null,"additionalInfo":null},{"columnName":"container_id","description":null,"dataType":"numeric","isNull":"Y","attributeName":null,"entityName":null,"columnOrder":8,"columnLength":null,"columnAlias":null,"additionalInfo":null},{"columnName":"user_id","description":null,"dataType":"integer","isNull":"N","attributeName":null,"entityName":null,"columnOrder":7,"columnLength":null,"columnAlias":null,"additionalInfo":null},{"columnName":"definition","description":null,"dataType":"text","isNull":"Y","attributeName":null,"entityName":null,"columnOrder":6,"columnLength":null,"columnAlias":null,"additionalInfo":null},{"columnName":"object_name","description":null,"dataType":"character varying","isNull":"Y","attributeName":null,"entityName":null,"columnOrder":5,"columnLength":"255","columnAlias":null,"additionalInfo":null},{"columnName":"object_id","description":null,"dataType":"character varying","isNull":"Y","attributeName":null,"entityName":null,"columnOrder":4,"columnLength":"255","columnAlias":null,"additionalInfo":null},{"columnName":"object_type","description":null,"dataType":"character varying","isNull":"Y","attributeName":null,"entityName":null,"columnOrder":3,"columnLength":"255","columnAlias":null,"additionalInfo":null},{"columnName":"activity_type","description":null,"dataType":"character varying","isNull":"Y","attributeName":null,"entityName":null,"columnOrder":2,"columnLength":"255","columnAlias":null,"additionalInfo":null},{"columnName":"feature_audit_item_id","description":null,"dataType":"integer","isNull":"Y","attributeName":null,"entityName":null,"columnOrder":1,"columnLength":null,"columnAlias":null,"additionalInfo":null},{"columnName":"nn","description":null,"dataType":"BIT","isNull":"N","attributeName":null,"entityName":null,"columnOrder":11,"columnLength":null,"columnAlias":null,"additionalInfo":null},{"columnName":"hh","description":null,"dataType":"_TEXT","isNull":"N","attributeName":null,"entityName":null,"columnOrder":12,"columnLength":null,"columnAlias":null,"additionalInfo":null},{"columnName":"ff","description":null,"dataType":"BIGINT","isNull":"N","attributeName":null,"entityName":null,"columnOrder":13,"columnLength":null,"columnAlias":null,"additionalInfo":null}],"rules":[{"ruleName":"Attribute Rule_activity_dt_5123","definition":"{\"severity\":\"Medium\",\"datasetSQLCondition\":\"\",\"selColumn\":\"activity_dt\",\"threshold\":\"0\",\"expressions\":{\"expr2\":\"\",\"expr1\":\"\"},\"operatorName\":\"is not null\",\"dataQualityDimension\":\"Completeness\",\"ruleTypeLabel\":\"Attribute\",\"ruleSQLConditionColumn\":\"\",\"unit\":\"Percentage\",\"primaryColumn\":\"activity_dt\",\"recordsCount\":\"0\",\"displayColumns\":\"feature_audit_item_id,activity_type,object_type,object_id,object_name,definition,user_id,container_id,partition_date,activity_dt\",\"columnNames\":\"\",\"successCriteria\":\"No bad records found\",\"ruleType\":\"Attribute\",\"percentage\":\"0\",\"name\":\"Attribute Rule\",\"id\":\"\",\"addedFromWizard\":true,\"operation\":\">\",\"operatorId\":\"7175d514-4f1c-4333-9983-145d7e26a1b8\",\"columnName\":\"activity_dt\"}","description":"","ruleType":"Attribute","ruleOrder":11,"tableName":"t_feature_audit_20220117","columnName":"activity_dt","isActive":"Y","dataQualityDimension":"Completeness","severity":"Medium","customFieldsValues":[],"ruleCategory":null,"isValid":null,"ruleKey":"0b3919fc-7ca6-4469-8f14-3eae086cd23f"},{"ruleName":"Duplicate Check Rule_3841","definition":"{\"severity\":\"Medium\",\"active\":\"Yes\",\"threshold\":\"0\",\"dataQuery\":\"\",\"schemaName\":\"public\",\"dataQualityDimension\":\"Unicity\",\"ruleTypeLabel\":\"DuplicateCheck\",\"unit\":\"Percentage\",\"primaryColumn\":\"activity_dt\",\"recordsCount\":\"0\",\"displayColumns\":\"activity_dt\",\"ruleSQLCondition\":\"\",\"columnNames\":\"\",\"successCriteria\":\"no duplicates found\",\"ruleType\":\"DuplicateCheck\",\"percentage\":\"0\",\"name\":\"Duplicate check\",\"id\":\"\",\"operation\":\"<\",\"workSchemaId\":\"0\"}","description":null,"ruleType":"DuplicateCheck","ruleOrder":0,"tableName":"t_feature_audit_20220117","columnName":"activity_dt","isActive":"Y","dataQualityDimension":"Unicity","severity":"Medium","customFieldsValues":[],"ruleCategory":null,"isValid":null,"ruleKey":"3aea247a-5cf4-4989-bdb3-ce927de34ba7"},{"ruleName":"Attribute Rule_partition_date_3604","definition":"{\"severity\":\"Medium\",\"datasetSQLCondition\":\"\",\"selColumn\":\"partition_date\",\"threshold\":\"0\",\"expressions\":{\"expr2\":\"\",\"expr1\":\"\"},\"operatorName\":\"is not null\",\"dataQualityDimension\":\"Completeness\",\"ruleTypeLabel\":\"Attribute\",\"ruleSQLConditionColumn\":\"\",\"unit\":\"Percentage\",\"primaryColumn\":\"partition_date\",\"recordsCount\":\"0\",\"displayColumns\":\"feature_audit_item_id,activity_type,object_type,object_id,object_name,definition,user_id,container_id,partition_date,activity_dt\",\"columnNames\":\"\",\"successCriteria\":\"No bad records found\",\"ruleType\":\"Attribute\",\"percentage\":\"0\",\"name\":\"Attribute Rule\",\"id\":\"\",\"addedFromWizard\":true,\"operation\":\">\",\"operatorId\":\"7175d514-4f1c-4333-9983-145d7e26a1b8\",\"columnName\":\"partition_date\"}","description":"","ruleType":"Attribute","ruleOrder":10,"tableName":"t_feature_audit_20220117","columnName":"partition_date","isActive":"Y","dataQualityDimension":"Completeness","severity":"Medium","customFieldsValues":[],"ruleCategory":null,"isValid":null,"ruleKey":"e5552360-802e-4c8a-bcc6-ca734b229f23"},{"ruleName":"Attribute Rule_container_id_4101","definition":"{\"severity\":\"Medium\",\"datasetSQLCondition\":\"\",\"selColumn\":\"container_id\",\"threshold\":\"0\",\"expressions\":{\"expr2\":\"\",\"expr1\":\"\"},\"operatorName\":\"is not null\",\"dataQualityDimension\":\"Completeness\",\"ruleTypeLabel\":\"Attribute\",\"ruleSQLConditionColumn\":\"\",\"unit\":\"Percentage\",\"primaryColumn\":\"container_id\",\"recordsCount\":\"0\",\"displayColumns\":\"feature_audit_item_id,activity_type,object_type,object_id,object_name,definition,user_id,container_id,partition_date,activity_dt\",\"columnNames\":\"\",\"successCriteria\":\"No bad records found\",\"ruleType\":\"Attribute\",\"percentage\":\"0\",\"name\":\"Attribute Rule\",\"id\":\"\",\"addedFromWizard\":true,\"operation\":\">\",\"operatorId\":\"7175d514-4f1c-4333-9983-145d7e26a1b8\",\"columnName\":\"container_id\"}","description":"","ruleType":"Attribute","ruleOrder":9,"tableName":"t_feature_audit_20220117","columnName":"container_id","isActive":"Y","dataQualityDimension":"Completeness","severity":"Medium","customFieldsValues":[],"ruleCategory":null,"isValid":null,"ruleKey":"15a16c08-d141-45ad-88c9-4503bf8ae83f"},{"ruleName":"SQL Query Rule_522","definition":"{\"severity\":\"Medium\",\"ruleQuery\":\"select * from public.t_feature_audit_20220117\",\"active\":\"Yes\",\"threshold\":\"0\",\"schemaName\":\"public\",\"dataQuery\":\"select count(*) from public.t_feature_audit_20220117\",\"dataQualityDimension\":\"Validity\",\"ruleTypeLabel\":\"SQL Query\",\"unit\":\"Percentage\",\"primaryColumn\":\"container_id\",\"recordsCount\":\"0\",\"columnNames\":\"\",\"successCriteria\":\"No bad records found\",\"ruleConditionType\":\"bad records\",\"ruleType\":\"SQLQuery\",\"percentage\":\"0\",\"name\":\"SQL query\",\"id\":\"\",\"operation\":\"<\",\"workSchemaId\":\"0\"}","description":null,"ruleType":"SQLQuery","ruleOrder":1,"tableName":"t_feature_audit_20220117","columnName":"container_id","isActive":"Y","dataQualityDimension":"Validity","severity":"Medium","customFieldsValues":[],"ruleCategory":null,"isValid":null,"ruleKey":"ca5bc88d-027b-45d8-8c23-cff0f3e7478e"},{"ruleName":"Attribute Rule_user_id_1946","definition":"{\"severity\":\"Medium\",\"datasetSQLCondition\":\"\",\"selColumn\":\"user_id\",\"threshold\":\"0\",\"expressions\":{\"expr2\":\"\",\"expr1\":\"\"},\"operatorName\":\"is not null\",\"dataQualityDimension\":\"Completeness\",\"ruleTypeLabel\":\"Attribute\",\"ruleSQLConditionColumn\":\"\",\"unit\":\"Percentage\",\"primaryColumn\":\"user_id\",\"recordsCount\":\"0\",\"displayColumns\":\"feature_audit_item_id,activity_type,object_type,object_id,object_name,definition,user_id,container_id,partition_date,activity_dt\",\"columnNames\":\"\",\"successCriteria\":\"No bad records found\",\"ruleType\":\"Attribute\",\"percentage\":\"0\",\"name\":\"Attribute Rule\",\"id\":\"\",\"addedFromWizard\":true,\"operation\":\">\",\"operatorId\":\"7175d514-4f1c-4333-9983-145d7e26a1b8\",\"columnName\":\"user_id\"}","description":"","ruleType":"Attribute","ruleOrder":8,"tableName":"t_feature_audit_20220117","columnName":"user_id","isActive":"Y","dataQualityDimension":"Completeness","severity":"Medium","customFieldsValues":[],"ruleCategory":null,"isValid":null,"ruleKey":"b3d45add-03f1-405b-beb7-b1a198b4901a"},{"ruleName":"Attribute Rule_definition_6504","definition":"{\"severity\":\"Medium\",\"datasetSQLCondition\":\"\",\"selColumn\":\"definition\",\"threshold\":\"0\",\"expressions\":{\"expr2\":\"\",\"expr1\":\"\"},\"operatorName\":\"is not null\",\"dataQualityDimension\":\"Completeness\",\"ruleTypeLabel\":\"Attribute\",\"ruleSQLConditionColumn\":\"\",\"unit\":\"Percentage\",\"primaryColumn\":\"definition\",\"recordsCount\":\"0\",\"displayColumns\":\"feature_audit_item_id,activity_type,object_type,object_id,object_name,definition,user_id,container_id,partition_date,activity_dt\",\"columnNames\":\"\",\"successCriteria\":\"No bad records found\",\"ruleType\":\"Attribute\",\"percentage\":\"0\",\"name\":\"Attribute Rule\",\"id\":\"\",\"addedFromWizard\":true,\"operation\":\">\",\"operatorId\":\"7175d514-4f1c-4333-9983-145d7e26a1b8\",\"columnName\":\"definition\"}","description":"","ruleType":"Attribute","ruleOrder":7,"tableName":"t_feature_audit_20220117","columnName":"definition","isActive":"Y","dataQualityDimension":"Completeness","severity":"Medium","customFieldsValues":[],"ruleCategory":null,"isValid":null,"ruleKey":"08a5dee5-ae18-4f97-adcd-1e2c98b9d37c"},{"ruleName":"Attribute Rule_object_name_8826","definition":"{\"severity\":\"Medium\",\"datasetSQLCondition\":\"\",\"selColumn\":\"object_name\",\"threshold\":\"0\",\"expressions\":{\"expr2\":\"\",\"expr1\":\"\"},\"operatorName\":\"is not null\",\"dataQualityDimension\":\"Completeness\",\"ruleTypeLabel\":\"Attribute\",\"ruleSQLConditionColumn\":\"\",\"unit\":\"Percentage\",\"primaryColumn\":\"object_name\",\"recordsCount\":\"0\",\"displayColumns\":\"feature_audit_item_id,activity_type,object_type,object_id,object_name,definition,user_id,container_id,partition_date,activity_dt\",\"columnNames\":\"\",\"successCriteria\":\"No bad records found\",\"ruleType\":\"Attribute\",\"percentage\":\"0\",\"name\":\"Attribute Rule\",\"id\":\"\",\"addedFromWizard\":true,\"operation\":\">\",\"operatorId\":\"7175d514-4f1c-4333-9983-145d7e26a1b8\",\"columnName\":\"object_name\"}","description":"","ruleType":"Attribute","ruleOrder":6,"tableName":"t_feature_audit_20220117","columnName":"object_name","isActive":"Y","dataQualityDimension":"Completeness","severity":"Medium","customFieldsValues":[],"ruleCategory":null,"isValid":null,"ruleKey":"bee8a0f9-6c39-4f34-b098-8a3f4a41890d"},{"ruleName":"Attribute Rule_object_id_3249","definition":"{\"severity\":\"Medium\",\"datasetSQLCondition\":\"\",\"selColumn\":\"object_id\",\"threshold\":\"0\",\"expressions\":{\"expr2\":\"\",\"expr1\":\"\"},\"operatorName\":\"is not null\",\"dataQualityDimension\":\"Completeness\",\"ruleTypeLabel\":\"Attribute\",\"ruleSQLConditionColumn\":\"\",\"unit\":\"Percentage\",\"primaryColumn\":\"object_id\",\"recordsCount\":\"0\",\"displayColumns\":\"feature_audit_item_id,activity_type,object_type,object_id,object_name,definition,user_id,container_id,partition_date,activity_dt\",\"columnNames\":\"\",\"successCriteria\":\"No bad records found\",\"ruleType\":\"Attribute\",\"percentage\":\"0\",\"name\":\"Attribute Rule\",\"id\":\"\",\"addedFromWizard\":true,\"operation\":\">\",\"operatorId\":\"7175d514-4f1c-4333-9983-145d7e26a1b8\",\"columnName\":\"object_id\"}","description":"","ruleType":"Attribute","ruleOrder":5,"tableName":"t_feature_audit_20220117","columnName":"object_id","isActive":"Y","dataQualityDimension":"Completeness","severity":"Medium","customFieldsValues":[],"ruleCategory":null,"isValid":null,"ruleKey":"eacf0386-9357-42e3-ba25-8c688acd2a16"},{"ruleName":"Attribute Rule_object_type_7506","definition":"{\"severity\":\"Medium\",\"datasetSQLCondition\":\"\",\"selColumn\":\"object_type\",\"threshold\":\"0\",\"expressions\":{\"expr2\":\"\",\"expr1\":\"\"},\"operatorName\":\"is not null\",\"dataQualityDimension\":\"Completeness\",\"ruleTypeLabel\":\"Attribute\",\"ruleSQLConditionColumn\":\"\",\"unit\":\"Percentage\",\"primaryColumn\":\"object_type\",\"recordsCount\":\"0\",\"displayColumns\":\"feature_audit_item_id,activity_type,object_type,object_id,object_name,definition,user_id,container_id,partition_date,activity_dt\",\"columnNames\":\"\",\"successCriteria\":\"No bad records found\",\"ruleType\":\"Attribute\",\"percentage\":\"0\",\"name\":\"Attribute Rule\",\"id\":\"\",\"addedFromWizard\":true,\"operation\":\">\",\"operatorId\":\"7175d514-4f1c-4333-9983-145d7e26a1b8\",\"columnName\":\"object_type\"}","description":"","ruleType":"Attribute","ruleOrder":4,"tableName":"t_feature_audit_20220117","columnName":"object_type","isActive":"Y","dataQualityDimension":"Completeness","severity":"Medium","customFieldsValues":[],"ruleCategory":null,"isValid":null,"ruleKey":"5bcc356d-fd41-4628-8e42-3ff229906a50"},{"ruleName":"Attribute Rule_activity_type_9030","definition":"{\"severity\":\"Medium\",\"datasetSQLCondition\":\"\",\"selColumn\":\"activity_type\",\"threshold\":\"0\",\"expressions\":{\"expr2\":\"\",\"expr1\":\"\"},\"operatorName\":\"is not null\",\"dataQualityDimension\":\"Completeness\",\"ruleTypeLabel\":\"Attribute\",\"ruleSQLConditionColumn\":\"\",\"unit\":\"Percentage\",\"primaryColumn\":\"activity_type\",\"recordsCount\":\"0\",\"displayColumns\":\"feature_audit_item_id,activity_type,object_type,object_id,object_name,definition,user_id,container_id,partition_date,activity_dt\",\"columnNames\":\"\",\"successCriteria\":\"No bad records found\",\"ruleType\":\"Attribute\",\"percentage\":\"0\",\"name\":\"Attribute Rule\",\"id\":\"\",\"addedFromWizard\":true,\"operation\":\">\",\"operatorId\":\"7175d514-4f1c-4333-9983-145d7e26a1b8\",\"columnName\":\"activity_type\"}","description":"","ruleType":"Attribute","ruleOrder":3,"tableName":"t_feature_audit_20220117","columnName":"activity_type","isActive":"Y","dataQualityDimension":"Completeness","severity":"Medium","customFieldsValues":[],"ruleCategory":null,"isValid":null,"ruleKey":"81fb457b-cc50-4f6a-9f1e-fba25a46715c"},{"ruleName":"Attribute Rule_feature_audit_item_id_2162","definition":"{\"severity\":\"Medium\",\"datasetSQLCondition\":\"\",\"selColumn\":\"feature_audit_item_id\",\"threshold\":\"0\",\"expressions\":{\"expr2\":\"\",\"expr1\":\"\"},\"operatorName\":\"is not null\",\"dataQualityDimension\":\"Completeness\",\"ruleTypeLabel\":\"Attribute\",\"ruleSQLConditionColumn\":\"\",\"unit\":\"Percentage\",\"primaryColumn\":\"feature_audit_item_id\",\"recordsCount\":\"0\",\"displayColumns\":\"feature_audit_item_id,activity_type,object_type,object_id,object_name,definition,user_id,container_id,partition_date,activity_dt\",\"columnNames\":\"\",\"successCriteria\":\"No bad records found\",\"ruleType\":\"Attribute\",\"percentage\":\"0\",\"name\":\"Attribute Rule\",\"id\":\"\",\"addedFromWizard\":true,\"operation\":\">\",\"operatorId\":\"7175d514-4f1c-4333-9983-145d7e26a1b8\",\"columnName\":\"feature_audit_item_id\"}","description":"","ruleType":"Attribute","ruleOrder":2,"tableName":"t_feature_audit_20220117","columnName":"feature_audit_item_id","isActive":"Y","dataQualityDimension":"Completeness","severity":"Medium","customFieldsValues":[],"ruleCategory":null,"isValid":null,"ruleKey":"6e816509-ac04-49ae-84f1-a53085a512a1"}],"relations":[{"foreignKeyTable":"t_feature_audit_20220117","foreignKeySchema":"public","childColumn":"activity_dt","primaryKeyTable":"t_feature_audit_20220117","primarykeySchema":"public","parentColumn":"object_id","relationType":"one-to-many"},{"foreignKeyTable":"t_feature_audit_20220117","foreignKeySchema":"public","childColumn":"object_id","primaryKeyTable":"t_feature_audit_20220117","primarykeySchema":"public","parentColumn":"object_name","relationType":"one-to-many"}],"sdvTemplate":null,"sampleDataSettingsJson":"{\"autoUpdate\":true,\"rowsToSample\":\"5000\",\"whereClause\":\"\",\"tableRowsLimit\":\"1000000\"}","datasourceName":null,"datasourceType":null,"uniqueColumns":null}],"workschemaName":null,"dmkey":"06079040-143d-499a-8dcd-dc25ea415e62"}