{"name":"Datamodel_4819","description":null,"dataSourceName":null,"tableDataModels":[{"tableName":"actor_1","schemaName":"sh","description":null,"columns":[{"columnName":"actor_id","description":null,"dataType":"INT2","isNull":"N","attributeName":null,"entityName":null,"columnOrder":1,"columnLength":null,"columnAlias":null,"additionalInfo":null}],"rules":[{"ruleName":"Duplicate Check Rule_718","definition":"{\"severity\":\"Medium\",\"active\":\"Yes\",\"threshold\":\"0\",\"dataQuery\":\"\",\"schemaName\":\"sh\",\"dataQualityDimension\":\"Unicity\",\"ruleTypeLabel\":\"DuplicateCheck\",\"unit\":\"Percentage\",\"primaryColumn\":\"actor_id\",\"recordsCount\":\"0\",\"displayColumns\":\"actor_id\",\"ruleSQLCondition\":\"\",\"columnNames\":\"\",\"successCriteria\":\"no duplicates found\",\"ruleType\":\"DuplicateCheck\",\"percentage\":\"0\",\"name\":\"Duplicate check\",\"id\":\"\",\"operation\":\"<\",\"workSchemaId\":\"0\"}","description":null,"ruleType":"DuplicateCheck","ruleOrder":0,"tableName":"actor_1","columnName":"actor_id","isActive":"Y","dataQualityDimension":"Unicity","severity":"Medium","customFieldsValues":[],"ruleCategory":null,"isValid":null,"ruleKey":"f359e044-2f30-47b7-9c20-0b45e2e7dff3"}],"relations":null,"sdvTemplate":null,"sampleDataSettingsJson":null,"datasourceName":null,"datasourceType":null,"uniqueColumns":null}],"workschemaName":null,"dmkey":"79ef8eed-64ba-47cb-912b-55598e7bd0db"}