{"name":"hanu_datamodel_3","description":null,"dataSourceName":null,"tableDataModels":[{"tableName":"ORDERS","schemaName":"ADMIN","description":null,"columns":[{"columnName":"ORDERID","description":null,"dataType":"BIGINT","isNull":"N","attributeName":null,"entityName":null,"columnOrder":null,"columnLength":null,"columnAlias":null,"additionalInfo":null},{"columnName":"CUSTOMERID","description":null,"dataType":"BIGINT","isNull":"N","attributeName":null,"entityName":null,"columnOrder":null,"columnLength":null,"columnAlias":null,"additionalInfo":null}],"rules":[{"ruleName":"SQL Query Rule","definition":"{\"severity\":\"Medium\",\"ruleQuery\":\"select * from ADMIN.ORDERS\",\"active\":\"Yes\",\"threshold\":\"0\",\"schemaName\":\"ADMIN\",\"dataQuery\":\"select count(*) from ADMIN.ORDERS\",\"dataQualityDimension\":\"Validity\",\"ruleTypeLabel\":\"SQL Query\",\"unit\":\"Percentage\",\"primaryColumn\":\"CUSTOMERID\",\"recordsCount\":\"0\",\"columnNames\":\"\",\"successCriteria\":\"Good record count is\",\"ruleConditionType\":\"good records\",\"ruleType\":\"SQLQuery\",\"percentage\":\"0\",\"name\":\"SQL query\",\"id\":\"\",\"operation\":\">\",\"workSchemaId\":\"0\"}","description":null,"ruleType":"SQLQuery","ruleOrder":0,"tableName":"ORDERS","columnName":"CUSTOMERID","isActive":"Y","dataQualityDimension":"Validity","severity":"Medium","customFieldsValues":[],"ruleCategory":null,"isValid":null,"ruleKey":null}],"relations":null,"sdvTemplate":null,"sampleDataSettingsJson":null,"datasourceName":null,"datasourceType":null,"uniqueColumns":null}],"workschemaName":null,"dmkey":"1271080756"}