{"dataflow":{"dfKey":"39bb454b-6be6-40c6-bf88-bd81ee309f1a","name":"Dataflow_183_upendar_6389","tags":null,"description":null,"definition":"{\"name\":\"Dataflow_183_upendar_6389\",\"engineVariableName\":\"\",\"components\":[{\"udfNames\":[],\"componentId\":0,\"componentName\":\"startComponent\",\"tableName\":\"\",\"category\":\"Start\",\"componentType\":\"UDF\",\"rank\":0,\"dataSourceName\":\"\",\"displayRows\":0,\"dependencies\":[],\"className\":\"com.datagaps.dataflow.models.UDFComponent\",\"executionOption\":\"\",\"excludeNotification\":\"Y\"},{\"workSheets\":[{\"name\":\"CustomerOverview\",\"datasetName\":\"CustomerOverview_922360\"},{\"name\":\"CustomerScatter\",\"datasetName\":\"CustomerScatter_252784\"},{\"name\":\"CustomerRank\",\"datasetName\":\"CustomerRank_137975\"}],\"reportViewPath\":\"Superstore/Customers\",\"filters\":[],\"parameters\":[],\"marks\":[],\"viewType\":\"dashboard\",\"viewTitle\":\"Workbook: Superstore\",\"componentId\":1,\"componentName\":\"Tableau 1\",\"tableName\":\"\",\"category\":\"Source\",\"componentType\":\"Tableau\",\"rank\":0,\"dataSourceName\":\"Tableau_nischal_10ax_upendar\",\"displayRows\":50,\"dependencies\":[],\"className\":\"com.datagaps.dataflow.models.BIComponent\",\"isCheckpointEnabled\":\"N\",\"dataSourceLogicalName\":\"\",\"executionOption\":\"\",\"excludeNotification\":\"N\"}],\"isDeleteWorkSchemaTable\":\"N\"}","parameters":"[{\"name\":\"limit_rows\",\"defValueInInteractiveMode\":\"limit 10\",\"defValueInBatchMode\":\"limit 1000\"}]","version":3,"maxComponentId":1,"livyOptions":null,"isDeleted":"N","userName":null,"type":"dataflow","environmentName":"","folderPath":"Dataflow/upendar","workSchemaName":null},"analysis":[],"datamodels":[],"tagDetails":[],"dataCompares":[]}