{"dataflow":{"dfKey":"4db8e347-f917-4ae3-a536-0d5824d73824","name":"Dataflow_4179_115","tags":null,"description":null,"definition":"{\"name\":\"Dataflow_4179_115\",\"engineVariableName\":\"\",\"components\":[{\"udfNames\":[],\"componentId\":0,\"componentName\":\"startComponent\",\"tableName\":\"\",\"category\":\"Start\",\"componentType\":\"UDF\",\"rank\":0,\"dataSourceName\":\"\",\"displayRows\":0,\"dependencies\":[],\"className\":\"com.datagaps.dataflow.models.UDFComponent\",\"executionOption\":\"\",\"excludeNotification\":\"Y\"},{\"workSheets\":[],\"reportViewPath\":\"Superstore_16552870825710/Customers\",\"filters\":[],\"parameters\":[],\"marks\":[],\"viewType\":\"dashboard\",\"viewTitle\":\"Workbook: Superstore\",\"dpi\":3.0,\"opacity\":0.1,\"color\":\"#ff182c\",\"compareMode\":\"Text\",\"componentId\":1,\"componentName\":\"Tableau Regression 1\",\"tableName\":\"\",\"category\":\"BI Analytics\",\"componentType\":\"Tableau Regression\",\"rank\":0,\"dataSourceName\":\"Tableau_nischal_10ax_upendar\",\"displayRows\":50,\"dependencies\":[],\"className\":\"com.datagaps.dataflow.models.TableauRegressionComponent\",\"isCheckpointEnabled\":\"N\",\"dataSourceLogicalName\":\"\",\"executionOption\":\"\",\"excludeNotification\":\"N\"},{\"workSheets\":[],\"reportViewPath\":\"PTAB/PTABReport\",\"filters\":[],\"parameters\":[],\"marks\":[],\"viewType\":\"dashboard\",\"viewTitle\":\"Workbook: PTAB\",\"dpi\":3.0,\"opacity\":0.1,\"color\":\"#ff182c\",\"compareMode\":\"Text\",\"componentId\":2,\"componentName\":\"Tableau Regression 2\",\"tableName\":\"\",\"category\":\"BI Analytics\",\"componentType\":\"Tableau Regression\",\"rank\":0,\"dataSourceName\":\"Tableau_nischal_10ax_upendar\",\"displayRows\":50,\"dependencies\":[],\"className\":\"com.datagaps.dataflow.models.TableauRegressionComponent\",\"isCheckpointEnabled\":\"N\",\"dataSourceLogicalName\":\"\",\"executionOption\":\"\",\"excludeNotification\":\"N\"},{\"sourceReport\":{\"workSheets\":[],\"filters\":[],\"parameters\":[],\"viewType\":\"worksheet\",\"viewTitle\":\"Workbook: Product Sales Dashboard\",\"marks\":[],\"reportViewPath\":\"ProductSalesDashboard/ProductSales\"},\"targetReport\":{\"workSheets\":[],\"filters\":[],\"parameters\":[],\"viewType\":\"worksheet\",\"viewTitle\":\"Workbook: Product Sales Dashboard\",\"marks\":[],\"reportViewPath\":\"ProductSalesDashboard/ProductSales\"},\"sourceDataSourceName\":\"Tableau_nischal_10ax_upendar\",\"targetDataSourceName\":\"Tableau_nischal_10ax_upendar\",\"sourceLogicalDataSourceName\":\"\",\"targeLogicalDataSourceName\":\"\",\"opacity\":0.1,\"color\":\"#ff182c\",\"compareMode\":\"Text\",\"dpi\":3.0,\"isApplySameFilters\":\"N\",\"isApplySameParameters\":\"N\",\"componentId\":3,\"componentName\":\"Tableau Upgrade 3\",\"tableName\":\"\",\"category\":\"BI Analytics\",\"componentType\":\"Tableau Upgrade\",\"rank\":0,\"displayRows\":0,\"dependencies\":[],\"className\":\"com.datagaps.dataflow.models.TableauUpgradeComponent\",\"executionOption\":\"\",\"excludeNotification\":\"N\"}],\"isDeleteWorkSchemaTable\":\"N\"}","parameters":"[{\"name\":\"limit_rows\",\"defValueInInteractiveMode\":\"limit 10\",\"defValueInBatchMode\":\"limit 1000\"}]","version":3,"maxComponentId":3,"livyOptions":null,"isDeleted":"N","userName":null,"type":"dataflow","environmentName":"","folderPath":"Dataflow/upendar","workSchemaName":null},"analysis":[],"datamodels":[],"tagDetails":[],"dataCompares":[]}